{"projects_unity_dontdrown.md":"uLglpapl","projects_unreal_untitledhorrorgame.md":"NbDJpYbf","projects_index.md":"9vby7f8q","projects_cryptraider.md":"WomQRS6H","projects_native_megaman.md":"wQL822XM","projects_software-rasterizer.md":"l6vk6Hmz","projects_unity_theholygrail.md":"Tjr75HOG","projects_chip-8.md":"J0tAsMCi","projects_native_vulkanshaderprocessor.md":"8yH4f3o-","software computer graphics_shaders_blendingtextures.md":"nmx7rGUg","projects_opengl-graphics.md":"3C7ijIJy","projects_unreal_supergalaxyrugby.md":"gWCePwUT","projects_environments.md":"_aI4Z1ly","software computer graphics_rasterizer_introduction.md":"rSmMLTdL","guides_build-ue5-vr.md":"-zAb0xJo","guides_rtg_height.md":"QBV0LRxk","projects_flaggame.md":"SoSiBcr6","software computer graphics_shaders_introduction.md":"4jDJS5rB","projects_software-raytracer.md":"kCYkPb_T","projects_city-scene.md":"a_C14WxN","projects_vulkan-rasterizer.md":"FgxYN_y8","projects_vulkan-raytracer.md":"V0K-EWjr","guides_rtg_index.md":"fIWXugd4","guides_index.md":"79A44Zee","software computer graphics_raytracing_introduction.md":"YsIMkoE_","vulkan_concepts.md":"OTqiReI-","projects_fuji-engine.md":"mEvfQ3r9","projects_unreal_amberthewitch.md":"YpI8Z1Z8","projects_grimreaper.md":"hPwMhw6W","projects_cubegame.md":"ckAoNvPE","vulkan_setup.md":"qPfFgDwJ","vulkan_introduction.md":"Fab6B6_u","index.md":"ED0c5uOB","software computer graphics_raytracing_ray-generation.md":"FWcdwDoi","software computer graphics_index.md":"YBBhUGgC"}
